pytdxmeasure/__init__.py
pytdxmeasure/actor.py
pytdxmeasure/binaryblob.py
pytdxmeasure/ccel.py
pytdxmeasure/cli.py
pytdxmeasure/rtmr.py
pytdxmeasure/tdeventlog.py
pytdxmeasure/tdquote.py
pytdxmeasure/tdreport.py
pytdxmeasure/utility.py
pytdxmeasure-0.0.9.data/scripts/tdx_eventlogs
pytdxmeasure-0.0.9.data/scripts/tdx_extend_rtmr
pytdxmeasure-0.0.9.data/scripts/tdx_quote
pytdxmeasure-0.0.9.data/scripts/tdx_tdreport
pytdxmeasure-0.0.9.data/scripts/tdx_verify_rtmr
pytdxmeasure-0.0.9.dist-info/LICENSE
pytdxmeasure-0.0.9.dist-info/METADATA
pytdxmeasure-0.0.9.dist-info/WHEEL
pytdxmeasure-0.0.9.dist-info/top_level.txt
pytdxmeasure-0.0.9.dist-info/RECORD
